scud/__init__.py
scud/_initialisation.py
scud/_utils.py
scud/_weights.py
scud/base.py
scud/binpca.py
scud/inverse_parameter_mappings.py
scud/linkfunctions.py
scud/lognormalizers.py
scud/logpartitions.py
scud/pca.py
scud/pca_sampling_parameters.py
scud/plnpca.py
scud/sample.py
scud/data/__init__.py
scud/data/_utils.py
scud/data/scrna.py
scud/data/datasets/scRT/counts.csv
scud/data/datasets/scRT/labels.csv
scud-0.0.6.dist-info/METADATA
scud-0.0.6.dist-info/WHEEL
scud-0.0.6.dist-info/top_level.txt
scud-0.0.6.dist-info/RECORD
