Metadata-Version: 2.1
Name: scud
Version: 0.0.6
Summary: Structured Principal Component Analysis
Author-email: Bastien Batardière <bastien.batardiere@gmail.com>
Maintainer-email: Bastien Batardière <bastien.batardiere@gmail.com>
License: MIT License
Classifier: License :: OSI Approved :: MIT License
Classifier: Development Status :: 3 - Alpha
Classifier: Programming Language :: Python
Requires-Python: >=3.7
Requires-Dist: numpy
Requires-Dist: optax
Requires-Dist: torch
Requires-Dist: jax
Requires-Dist: pandas
Requires-Dist: scikit_learn
Requires-Dist: matplotlib
Requires-Dist: seaborn
Requires-Dist: tqdm
Provides-Extra: tests
Requires-Dist: pytest; extra == "tests"
Requires-Dist: pytest_lazy_fixture; extra == "tests"
Provides-Extra: doc
Requires-Dist: sphinx; extra == "doc"
Requires-Dist: sphinx_rtd_theme; extra == "doc"
